{
  "expectations": [
    {
      "eval_id": 201,
      "eval_name": "ai-1-2-3-10-4-mece",
      "configuration": "with_skill",
      "expectation_id": "mece-dimension",
      "text": "The output should state the decomposition dimension or method.",
      "passed_runs": 1,
      "total_runs": 1,
      "pass_rate": 1.0,
      "unstable": false
    },
    {
      "eval_id": 201,
      "eval_name": "ai-1-2-3-10-4-mece",
      "configuration": "with_skill",
      "expectation_id": "mece-check",
      "text": "The output should include a MECE-style completeness or independence check.",
      "passed_runs": 1,
      "total_runs": 1,
      "pass_rate": 1.0,
      "unstable": false
    },
    {
      "eval_id": 201,
      "eval_name": "ai-1-2-3-10-4-mece",
      "configuration": "with_skill",
      "expectation_id": "mece-priority",
      "text": "The output should conclude with action priorities or next-step guidance.",
      "passed_runs": 1,
      "total_runs": 1,
      "pass_rate": 1.0,
      "unstable": false
    },
    {
      "eval_id": 201,
      "eval_name": "ai-1-2-3-10-4-mece",
      "configuration": "without_skill",
      "expectation_id": "mece-dimension",
      "text": "The output should state the decomposition dimension or method.",
      "passed_runs": 0,
      "total_runs": 1,
      "pass_rate": 0.0,
      "unstable": false
    },
    {
      "eval_id": 201,
      "eval_name": "ai-1-2-3-10-4-mece",
      "configuration": "without_skill",
      "expectation_id": "mece-check",
      "text": "The output should include a MECE-style completeness or independence check.",
      "passed_runs": 1,
      "total_runs": 1,
      "pass_rate": 1.0,
      "unstable": false
    },
    {
      "eval_id": 201,
      "eval_name": "ai-1-2-3-10-4-mece",
      "configuration": "without_skill",
      "expectation_id": "mece-priority",
      "text": "The output should conclude with action priorities or next-step guidance.",
      "passed_runs": 1,
      "total_runs": 1,
      "pass_rate": 1.0,
      "unstable": false
    },
    {
      "eval_id": 202,
      "eval_name": "mece",
      "configuration": "with_skill",
      "expectation_id": "ask-missing-info",
      "text": "The output should ask for the missing context first.",
      "passed_runs": 1,
      "total_runs": 1,
      "pass_rate": 1.0,
      "unstable": false
    },
    {
      "eval_id": 202,
      "eval_name": "mece",
      "configuration": "with_skill",
      "expectation_id": "no-premature-breakdown",
      "text": "The output should not jump straight into a complete breakdown when the input is too vague.",
      "passed_runs": 1,
      "total_runs": 1,
      "pass_rate": 1.0,
      "unstable": false
    },
    {
      "eval_id": 202,
      "eval_name": "mece",
      "configuration": "without_skill",
      "expectation_id": "ask-missing-info",
      "text": "The output should ask for the missing context first.",
      "passed_runs": 1,
      "total_runs": 1,
      "pass_rate": 1.0,
      "unstable": false
    },
    {
      "eval_id": 202,
      "eval_name": "mece",
      "configuration": "without_skill",
      "expectation_id": "no-premature-breakdown",
      "text": "The output should not jump straight into a complete breakdown when the input is too vague.",
      "passed_runs": 1,
      "total_runs": 1,
      "pass_rate": 1.0,
      "unstable": false
    }
  ]
}